<?xml version="1.0" encoding="UTF-8"?>
<!DOCTYPE mapper PUBLIC "-//mybatis.org//DTD Mapper 3.0//EN" "http://mybatis.org/dtd/mybatis-3-mapper.dtd">
<mapper namespace="com.ssafit.model.dao.LikesDao">
	<select id="selectAllByUser" parameterType="int"
		resultType="Likes">
		SELECT *
		FROM likes
		WHERE userIdx = #{userIdx};
	</select>

	<select id="selectAllByVideo" parameterType="int"
		resultType="Likes">
		SELECT *
		FROM likes
		WHERE videoIdx = #{videoIdx};
	</select>

	<select id="selectLikes" parameterType="Likes" resultType="Likes">
		SELECT *
		FROM likes
		WHERE userIdx = #{userIdx} AND videoIdx = #{videoIdx};
	</select>

	<insert id="insertLikes" parameterType="Likes" keyProperty="idx"
		useGeneratedKeys="true">
		INSERT INTO likes (userIdx, videoIdx) VALUES
		(#{userIdx}, #{videoIdx});
		UPDATE video
		SET likeCnt = likeCnt+1
		WHERE idx = #{videoIdx};
	</insert>

	<delete id="deleteLikes" parameterType="int">
		DELETE
		FROM likes
		WHERE idx =
		#{idx};
		UPDATE video
		SET likeCnt = likeCnt-1
		WHERE idx = #{videoIdx};
	</delete>
</mapper>